{"id":"sqlalchemy.ext.declarative","path":"/usr/local/lib/python3.10/dist-packages/sqlalchemy/ext/declarative/__init__.py","mtime":1678433730,"size":1818,"hash":"549bbc4b579fc62976d16e3c7c99690e7ea01e8aceb9d9f9a77fa517bd96709f","data_mtime":1682578022,"dependencies":["sqlalchemy.ext.declarative.extensions","sqlalchemy.orm.decl_api","sqlalchemy.util","sqlalchemy","builtins","abc","sqlalchemy.event","sqlalchemy.event.registry","sqlalchemy.inspection","sqlalchemy.log","sqlalchemy.orm","sqlalchemy.orm.base","sqlalchemy.orm.clsregistry","sqlalchemy.orm.descriptor_props","sqlalchemy.orm.interfaces","sqlalchemy.orm.mapper","sqlalchemy.sql","sqlalchemy.sql.base","sqlalchemy.sql.cache_key","sqlalchemy.sql.elements","sqlalchemy.sql.operators","sqlalchemy.sql.roles","sqlalchemy.sql.schema","sqlalchemy.sql.type_api","sqlalchemy.sql.visitors","sqlalchemy.util.deprecations","sqlalchemy.util.langhelpers","typing"],"suppressed":[],"options":{"platform":"linux","disallow_untyped_decorators":false,"disallow_untyped_defs":false,"strict_optional":true,"disallow_incomplete_defs":false,"always_true":[],"strict_equality":false,"disallow_any_decorated":false,"warn_unreachable":false,"disable_bytearray_promotion":false,"allow_untyped_globals":false,"disallow_any_unimported":false,"follow_imports_for_stubs":false,"enabled_error_codes":[],"disabled_error_codes":[],"warn_return_any":false,"warn_unused_ignores":false,"local_partial_types":false,"disallow_any_generics":false,"bazel":false,"disallow_untyped_calls":false,"strict_concatenate":false,"disallow_any_explicit":false,"disable_memoryview_promotion":false,"always_false":[],"check_untyped_defs":false,"mypyc":false,"enable_error_code":[],"plugins":[],"disallow_subclassing_any":false,"allow_redefinition":false,"follow_imports":"silent","disable_error_code":[],"implicit_reexport":true,"implicit_optional":false,"ignore_missing_imports":true,"disallow_any_expr":false,"warn_no_return":true,"ignore_errors":false},"dep_prios":[5,5,10,20,5,30,30,30,30,30,30,30,30,30,30,30,30,30,30,30,30,30,30,30,30,30,30,30],"dep_lines":[10,14,13,13,1,1,1,1,1,1,1,1,1,1,1,1,1,1,1,1,1,1,1,1,1,1,1,1],"interface_hash":"a11da1beee44998b929b1807073fa4a11d2414f0c16eec17612f7768f8a1e59e","version_id":"1.2.0","ignore_all":true,"plugin_data":null}