{"id":"torch._utils_internal","path":"/usr/local/lib/python3.10/dist-packages/torch/_utils_internal.py","mtime":1679531154,"size":1687,"hash":"8f2d5c7d4018cdd63b6047d607d5bec149abfb015d519f7d784a9e70a6fb2739","data_mtime":1682578014,"dependencies":["os","sys","tempfile","builtins","abc","posixpath","typing"],"suppressed":[],"options":{"platform":"linux","disallow_untyped_decorators":false,"disallow_untyped_defs":false,"strict_optional":true,"disallow_incomplete_defs":false,"always_true":[],"strict_equality":false,"disallow_any_decorated":false,"warn_unreachable":false,"disable_bytearray_promotion":false,"allow_untyped_globals":false,"disallow_any_unimported":false,"follow_imports_for_stubs":false,"enabled_error_codes":[],"disabled_error_codes":[],"warn_return_any":false,"warn_unused_ignores":false,"local_partial_types":false,"disallow_any_generics":false,"bazel":false,"disallow_untyped_calls":false,"strict_concatenate":false,"disallow_any_explicit":false,"disable_memoryview_promotion":false,"always_false":[],"check_untyped_defs":false,"mypyc":false,"enable_error_code":[],"plugins":[],"disallow_subclassing_any":false,"allow_redefinition":false,"follow_imports":"silent","disable_error_code":[],"implicit_reexport":true,"implicit_optional":false,"ignore_missing_imports":true,"disallow_any_expr":false,"warn_no_return":true,"ignore_errors":false},"dep_prios":[10,10,10,5,30,30,30],"dep_lines":[1,2,3,1,1,1,1],"interface_hash":"e8ff12ce278522ea2cf784ebbdbd3cfa41b99bb8ebf47acb76fb995133e3f18c","version_id":"1.2.0","ignore_all":true,"plugin_data":null}