{"data_mtime":1685575590,"dep_lines":[25,26,23,15,16,17,19,1,1,1,1,1,1,1,1,1,1,1,1,1,31],"dep_prios":[5,5,5,10,10,5,5,5,20,20,20,30,30,30,30,30,30,30,30,30,5],"dependencies":["torchmetrics.utilities.checks","torchmetrics.utilities.imports","torch.linalg","math","warnings","typing","torch","builtins","torch.distributed","multiprocessing.reduction","torch.nn","abc","torch._C","torch._C._VariableFunctions","torch._tensor","torch.fft","torch.functional","torch.types","torchmetrics.utilities","typing_extensions"],"hash":"041dbb50f012b4aa12cc7b2bf9694e062728e0e8fa1128ad645385330ab045bc","id":"torchmetrics.functional.audio.sdr","ignore_all":true,"interface_hash":"e9447db5018dee0a8a4b9e70d6e93cb9e3b5b9faba712a7ad937651048efe7fb","mtime":1679530438,"options":{"allow_redefinition":false,"allow_untyped_globals":false,"always_false":[],"always_true":[],"bazel":false,"check_untyped_defs":false,"disable_bytearray_promotion":false,"disable_error_code":[],"disable_memoryview_promotion":false,"disabled_error_codes":[],"disallow_any_decorated":false,"disallow_any_explicit":false,"disallow_any_expr":false,"disallow_any_generics":false,"disallow_any_unimported":false,"disallow_incomplete_defs":false,"disallow_subclassing_any":false,"disallow_untyped_calls":false,"disallow_untyped_decorators":false,"disallow_untyped_defs":false,"enable_error_code":[],"enabled_error_codes":[],"follow_imports":"silent","follow_imports_for_stubs":false,"ignore_errors":false,"ignore_missing_imports":true,"implicit_optional":false,"implicit_reexport":true,"local_partial_types":false,"mypyc":false,"platform":"linux","plugins":[],"strict_concatenate":false,"strict_equality":false,"strict_optional":true,"warn_no_return":true,"warn_return_any":false,"warn_unreachable":false,"warn_unused_ignores":false},"path":"/home/afe/.local/lib/python3.10/site-packages/torchmetrics/functional/audio/sdr.py","plugin_data":null,"size":9548,"suppressed":["fast_bss_eval.torch.cgd"],"version_id":"1.2.0"}