{"data_mtime":1685575560,"dep_lines":[4,5,7,8,9,10,11,16,17,20,21,22,25,5,25,29,30,1,1,1,1,1,1,1,1,1,1,1,1,1,1,1,1,1,1,1,1,1,1,1,1,1,1,1,1,1,1,1,1,1,1,1,1,28,27],"dep_prios":[5,10,5,5,5,5,5,5,5,5,5,5,10,5,5,5,5,5,20,20,30,30,30,30,30,30,30,30,30,30,30,30,30,30,30,30,30,30,30,30,30,30,30,30,30,30,30,30,20,20,20,20,30,5,5],"dependencies":["sympy.core.basic","sympy.core.sympify","sympy.core.cache","sympy.core.relational","sympy.core.sorting","sympy.polys.domains","sympy.polys.polyerrors","sympy.polys.polyfuncs","sympy.polys.polyroots","sympy.polys.polytools","sympy.polys.rationaltools","sympy.polys.rootisolation","sympy.utilities.lambdify","sympy.core","sympy.utilities","sympy.multipledispatch","itertools","builtins","pyexpat.model","pyexpat.errors","_typeshed","abc","array","ctypes","mmap","pickle","sympy.core._print_helpers","sympy.core.add","sympy.core.assumptions","sympy.core.core","sympy.core.evalf","sympy.core.expr","sympy.core.function","sympy.core.numbers","sympy.core.singleton","sympy.core.symbol","sympy.logic","sympy.logic.boolalg","sympy.polys.domains.characteristiczero","sympy.polys.domains.domain","sympy.polys.domains.field","sympy.polys.domains.rationalfield","sympy.polys.domains.ring","sympy.polys.domains.simpledomain","sympy.utilities.decorator","sympy.utilities.iterables","typing","typing_extensions","multiprocessing.reduction","torch","torch.distributed","torch.nn","types"],"hash":"608d557de7cc2370842f9f8f5cd9a0a527047ace4051e3d70a1154f8a877bde9","id":"sympy.polys.rootoftools","ignore_all":true,"interface_hash":"dc84b19b71099d9fc19e61c99cc69ddc401821ca400ef06ec78a073a557c4e9a","mtime":1679000374,"options":{"allow_redefinition":false,"allow_untyped_globals":false,"always_false":[],"always_true":[],"bazel":false,"check_untyped_defs":false,"disable_bytearray_promotion":false,"disable_error_code":[],"disable_memoryview_promotion":false,"disabled_error_codes":[],"disallow_any_decorated":false,"disallow_any_explicit":false,"disallow_any_expr":false,"disallow_any_generics":false,"disallow_any_unimported":false,"disallow_incomplete_defs":false,"disallow_subclassing_any":false,"disallow_untyped_calls":false,"disallow_untyped_decorators":false,"disallow_untyped_defs":false,"enable_error_code":[],"enabled_error_codes":[],"follow_imports":"silent","follow_imports_for_stubs":false,"ignore_errors":false,"ignore_missing_imports":true,"implicit_optional":false,"implicit_reexport":true,"local_partial_types":false,"mypyc":false,"platform":"linux","plugins":[],"strict_concatenate":false,"strict_equality":false,"strict_optional":true,"warn_no_return":true,"warn_return_any":false,"warn_unreachable":false,"warn_unused_ignores":false},"path":"/usr/local/lib/python3.10/dist-packages/sympy/polys/rootoftools.py","plugin_data":null,"size":40969,"suppressed":["mpmath.libmp.libmpf","mpmath"],"version_id":"1.2.0"}