{".class":"MypyFile","_fullname":"torchmetrics.audio.stoi","future_import_flags":[],"is_partial_stub_package":false,"is_stub":false,"names":{".class":"SymbolTable","Any":{".class":"SymbolTableNode","cross_ref":"typing.Any","kind":"Gdef"},"Metric":{".class":"SymbolTableNode","cross_ref":"torchmetrics.metric.Metric","kind":"Gdef"},"ShortTimeObjectiveIntelligibility":{".class":"SymbolTableNode","kind":"Gdef","node":{".class":"TypeInfo","_promote":[],"abstract_attributes":[],"alt_promote":null,"bases":["torchmetrics.metric.Metric"],"dataclass_transform_spec":null,"declared_metaclass":null,"defn":{".class":"ClassDef","fullname":"torchmetrics.audio.stoi.ShortTimeObjectiveIntelligibility","name":"ShortTimeObjectiveIntelligibility","type_vars":[]},"deletable_attributes":[],"flags":[],"fullname":"torchmetrics.audio.stoi.ShortTimeObjectiveIntelligibility","has_param_spec_type":false,"metaclass_type":"abc.ABCMeta","metadata":{},"module_name":"torchmetrics.audio.stoi","mro":["torchmetrics.audio.stoi.ShortTimeObjectiveIntelligibility","torchmetrics.metric.Metric","torch.nn.modules.module.Module","abc.ABC","builtins.object"],"names":{".class":"SymbolTable","__init__":{".class":"SymbolTableNode","kind":"Mdef","node":{".class":"FuncDef","abstract_status":0,"arg_kinds":[0,0,1,4],"arg_names":["self","fs","extended","kwargs"],"dataclass_transform_spec":null,"flags":[],"fullname":"torchmetrics.audio.stoi.ShortTimeObjectiveIntelligibility.__init__","name":"__init__","type":{".class":"CallableType","arg_kinds":[0,0,1,4],"arg_names":["self","fs","extended","kwargs"],"arg_types":["torchmetrics.audio.stoi.ShortTimeObjectiveIntelligibility","builtins.int","builtins.bool",{".class":"AnyType","missing_import_name":null,"source_any":null,"type_of_any":2}],"bound_args":[],"def_extras":{"first_arg":"self"},"fallback":"builtins.function","from_concatenate":false,"implicit":false,"is_ellipsis_args":false,"name":"__init__ of ShortTimeObjectiveIntelligibility","ret_type":{".class":"NoneType"},"type_guard":null,"unpack_kwargs":false,"variables":[]}}},"compute":{".class":"SymbolTableNode","kind":"Mdef","node":{".class":"FuncDef","abstract_status":0,"arg_kinds":[0],"arg_names":["self"],"dataclass_transform_spec":null,"flags":[],"fullname":"torchmetrics.audio.stoi.ShortTimeObjectiveIntelligibility.compute","name":"compute","type":{".class":"CallableType","arg_kinds":[0],"arg_names":["self"],"arg_types":["torchmetrics.audio.stoi.ShortTimeObjectiveIntelligibility"],"bound_args":[],"def_extras":{"first_arg":"self"},"fallback":"builtins.function","from_concatenate":false,"implicit":false,"is_ellipsis_args":false,"name":"compute of ShortTimeObjectiveIntelligibility","ret_type":"torch._tensor.Tensor","type_guard":null,"unpack_kwargs":false,"variables":[]}}},"extended":{".class":"SymbolTableNode","implicit":true,"kind":"Mdef","node":{".class":"Var","flags":["is_inferred"],"fullname":"torchmetrics.audio.stoi.ShortTimeObjectiveIntelligibility.extended","name":"extended","type":"builtins.bool"}},"fs":{".class":"SymbolTableNode","implicit":true,"kind":"Mdef","node":{".class":"Var","flags":["is_inferred"],"fullname":"torchmetrics.audio.stoi.ShortTimeObjectiveIntelligibility.fs","name":"fs","type":"builtins.int"}},"full_state_update":{".class":"SymbolTableNode","kind":"Mdef","node":{".class":"Var","flags":["is_initialized_in_class","is_ready","has_explicit_value"],"fullname":"torchmetrics.audio.stoi.ShortTimeObjectiveIntelligibility.full_state_update","name":"full_state_update","type":"builtins.bool"}},"higher_is_better":{".class":"SymbolTableNode","kind":"Mdef","node":{".class":"Var","flags":["is_initialized_in_class","is_ready","has_explicit_value"],"fullname":"torchmetrics.audio.stoi.ShortTimeObjectiveIntelligibility.higher_is_better","name":"higher_is_better","type":"builtins.bool"}},"is_differentiable":{".class":"SymbolTableNode","kind":"Mdef","node":{".class":"Var","flags":["is_initialized_in_class","is_ready","has_explicit_value"],"fullname":"torchmetrics.audio.stoi.ShortTimeObjectiveIntelligibility.is_differentiable","name":"is_differentiable","type":"builtins.bool"}},"sum_stoi":{".class":"SymbolTableNode","kind":"Mdef","node":{".class":"Var","flags":["is_initialized_in_class","is_ready"],"fullname":"torchmetrics.audio.stoi.ShortTimeObjectiveIntelligibility.sum_stoi","name":"sum_stoi","type":"torch._tensor.Tensor"}},"total":{".class":"SymbolTableNode","kind":"Mdef","node":{".class":"Var","flags":["is_initialized_in_class","is_ready"],"fullname":"torchmetrics.audio.stoi.ShortTimeObjectiveIntelligibility.total","name":"total","type":"torch._tensor.Tensor"}},"update":{".class":"SymbolTableNode","kind":"Mdef","node":{".class":"FuncDef","abstract_status":0,"arg_kinds":[0,0,0],"arg_names":["self","preds","target"],"dataclass_transform_spec":null,"flags":[],"fullname":"torchmetrics.audio.stoi.ShortTimeObjectiveIntelligibility.update","name":"update","type":{".class":"CallableType","arg_kinds":[0,0,0],"arg_names":["self","preds","target"],"arg_types":["torchmetrics.audio.stoi.ShortTimeObjectiveIntelligibility","torch._tensor.Tensor","torch._tensor.Tensor"],"bound_args":[],"def_extras":{"first_arg":"self"},"fallback":"builtins.function","from_concatenate":false,"implicit":false,"is_ellipsis_args":false,"name":"update of ShortTimeObjectiveIntelligibility","ret_type":{".class":"NoneType"},"type_guard":null,"unpack_kwargs":false,"variables":[]}}}},"self_type":null,"slots":null,"tuple_type":null,"type_vars":[],"typeddict_type":null}},"Tensor":{".class":"SymbolTableNode","cross_ref":"torch._tensor.Tensor","kind":"Gdef"},"_PYSTOI_AVAILABLE":{".class":"SymbolTableNode","cross_ref":"torchmetrics.utilities.imports._PYSTOI_AVAILABLE","kind":"Gdef"},"__annotations__":{".class":"SymbolTableNode","kind":"Gdef","node":{".class":"Var","flags":["is_ready"],"fullname":"torchmetrics.audio.stoi.__annotations__","name":"__annotations__","type":{".class":"Instance","args":["builtins.str",{".class":"AnyType","missing_import_name":null,"source_any":null,"type_of_any":6}],"type_ref":"builtins.dict"}}},"__doc__":{".class":"SymbolTableNode","kind":"Gdef","node":{".class":"Var","flags":["is_ready"],"fullname":"torchmetrics.audio.stoi.__doc__","name":"__doc__","type":"builtins.str"}},"__doctest_requires__":{".class":"SymbolTableNode","kind":"Gdef","node":{".class":"Var","flags":["is_inferred","has_explicit_value"],"fullname":"torchmetrics.audio.stoi.__doctest_requires__","name":"__doctest_requires__","type":{".class":"Instance","args":["builtins.str",{".class":"Instance","args":["builtins.str"],"type_ref":"builtins.list"}],"type_ref":"builtins.dict"}}},"__file__":{".class":"SymbolTableNode","kind":"Gdef","node":{".class":"Var","flags":["is_ready"],"fullname":"torchmetrics.audio.stoi.__file__","name":"__file__","type":"builtins.str"}},"__name__":{".class":"SymbolTableNode","kind":"Gdef","node":{".class":"Var","flags":["is_ready"],"fullname":"torchmetrics.audio.stoi.__name__","name":"__name__","type":"builtins.str"}},"__package__":{".class":"SymbolTableNode","kind":"Gdef","node":{".class":"Var","flags":["is_ready"],"fullname":"torchmetrics.audio.stoi.__package__","name":"__package__","type":"builtins.str"}},"short_time_objective_intelligibility":{".class":"SymbolTableNode","cross_ref":"torchmetrics.functional.audio.stoi.short_time_objective_intelligibility","kind":"Gdef"},"tensor":{".class":"SymbolTableNode","cross_ref":"torch._C._VariableFunctions.tensor","kind":"Gdef"}},"path":"/home/afe/.local/lib/python3.10/site-packages/torchmetrics/audio/stoi.py"}