{"data_mtime":1682578450,"dep_lines":[19,21,26,27,28,29,30,31,32,34,35,36,37,33,14,15,16,18,23,1,1,1,1,1,1,1,1,1,1,1,1,1,1,1,1,1,1,1,1,1,1,1,1,1,1,1,1,1,1,1,1,1,1,1,1,1,1,1,1,1,1,1,1,1,1,1,1,25,24,40],"dep_prios":[5,5,5,5,5,5,5,5,5,5,5,5,5,5,10,10,5,5,10,5,20,20,20,20,20,20,20,20,20,20,20,30,30,30,30,30,30,30,30,30,30,30,30,30,30,30,30,30,30,30,30,30,30,30,30,30,30,30,30,30,30,30,30,30,30,30,30,5,5,10],"dependencies":["lightning_utilities.core.apply_func","torch.utils.data","pytorch_lightning.accelerators.ipu","pytorch_lightning.overrides.base","pytorch_lightning.plugins.precision","pytorch_lightning.strategies.parallel","pytorch_lightning.strategies.strategy","pytorch_lightning.strategies.utils","pytorch_lightning.trainer.states","pytorch_lightning.utilities.data","pytorch_lightning.utilities.exceptions","pytorch_lightning.utilities.model_helpers","pytorch_lightning.utilities.types","pytorch_lightning.utilities","json","os","typing","torch","pytorch_lightning","builtins","alembic.util.sqla_compat","pyexpat.model","sqlalchemy.engine.url","logging","torch.distributed","alembic.util","pyexpat.errors","sys","multiprocessing.reduction","torch.nn","alembic.ddl","_collections_abc","_typeshed","abc","array","contextlib","ctypes","json.encoder","mmap","pickle","pytorch_lightning.accelerators","pytorch_lightning.accelerators.accelerator","pytorch_lightning.core","pytorch_lightning.core.hooks","pytorch_lightning.core.mixins","pytorch_lightning.core.mixins.hparams_mixin","pytorch_lightning.core.module","pytorch_lightning.overrides","pytorch_lightning.plugins","pytorch_lightning.plugins.precision.precision_plugin","pytorch_lightning.trainer","pytorch_lightning.trainer.connectors","pytorch_lightning.trainer.connectors.data_connector","pytorch_lightning.trainer.trainer","torch._C","torch._C._VariableFunctions","torch._tensor","torch.nn.modules","torch.nn.modules.module","torch.optim","torch.optim.optimizer","torch.types","torch.utils","torch.utils.data.dataloader","torch.utils.data.sampler","types","typing_extensions"],"hash":"91758a5ab25d1ea276de5044225e4452eb1b436c4f0f9d6edc89409ae0d33604","id":"pytorch_lightning.strategies.ipu","ignore_all":true,"interface_hash":"ede7503c95a09a794a9d8bea2e8c1ba8d8a234d64e4f6f25fec4f98c919cb6df","mtime":1680226687,"options":{"allow_redefinition":false,"allow_untyped_globals":false,"always_false":[],"always_true":[],"bazel":false,"check_untyped_defs":false,"disable_bytearray_promotion":false,"disable_error_code":[],"disable_memoryview_promotion":false,"disabled_error_codes":[],"disallow_any_decorated":false,"disallow_any_explicit":false,"disallow_any_expr":false,"disallow_any_generics":false,"disallow_any_unimported":false,"disallow_incomplete_defs":false,"disallow_subclassing_any":false,"disallow_untyped_calls":false,"disallow_untyped_decorators":false,"disallow_untyped_defs":false,"enable_error_code":[],"enabled_error_codes":[],"follow_imports":"silent","follow_imports_for_stubs":false,"ignore_errors":false,"ignore_missing_imports":true,"implicit_optional":false,"implicit_reexport":true,"local_partial_types":false,"mypyc":false,"platform":"linux","plugins":[],"strict_concatenate":false,"strict_equality":false,"strict_optional":true,"warn_no_return":true,"warn_return_any":false,"warn_unreachable":false,"warn_unused_ignores":false},"path":"/home/afe/.local/lib/python3.10/site-packages/pytorch_lightning/strategies/ipu.py","plugin_data":null,"size":17007,"suppressed":["lightning_fabric.utilities.cloud_io","lightning_fabric.plugins","poptorch"],"version_id":"1.2.0"}