{".class":"MypyFile","_fullname":"pytorch_lightning.utilities.combined_loader","future_import_flags":[],"is_partial_stub_package":false,"is_stub":false,"names":{".class":"SymbolTable","Any":{".class":"SymbolTableNode","cross_ref":"typing.Any","kind":"Gdef"},"Callable":{".class":"SymbolTableNode","cross_ref":"typing.Callable","kind":"Gdef"},"CombinedLoader":{".class":"SymbolTableNode","kind":"Gdef","node":{".class":"TypeInfo","_promote":[],"abstract_attributes":[],"alt_promote":null,"bases":[{".class":"Instance","args":[{".class":"AnyType","missing_import_name":null,"source_any":null,"type_of_any":4}],"type_ref":"typing.Iterable"}],"dataclass_transform_spec":null,"declared_metaclass":null,"defn":{".class":"ClassDef","fullname":"pytorch_lightning.utilities.combined_loader.CombinedLoader","name":"CombinedLoader","type_vars":[]},"deletable_attributes":[],"flags":[],"fullname":"pytorch_lightning.utilities.combined_loader.CombinedLoader","has_param_spec_type":false,"metaclass_type":"abc.ABCMeta","metadata":{},"module_name":"pytorch_lightning.utilities.combined_loader","mro":["pytorch_lightning.utilities.combined_loader.CombinedLoader","typing.Iterable","builtins.object"],"names":{".class":"SymbolTable","__init__":{".class":"SymbolTableNode","kind":"Mdef","node":{".class":"FuncDef","abstract_status":0,"arg_kinds":[0,0,1],"arg_names":["self","iterables","mode"],"dataclass_transform_spec":null,"flags":[],"fullname":"pytorch_lightning.utilities.combined_loader.CombinedLoader.__init__","name":"__init__","type":{".class":"CallableType","arg_kinds":[0,0,1],"arg_names":["self","iterables","mode"],"arg_types":["pytorch_lightning.utilities.combined_loader.CombinedLoader",{".class":"AnyType","missing_import_name":null,"source_any":null,"type_of_any":2},{".class":"TypeAliasType","args":[],"type_ref":"pytorch_lightning.utilities.combined_loader._LITERAL_SUPPORTED_MODES"}],"bound_args":[],"def_extras":{"first_arg":"self"},"fallback":"builtins.function","from_concatenate":false,"implicit":false,"is_ellipsis_args":false,"name":"__init__ of CombinedLoader","ret_type":{".class":"NoneType"},"type_guard":null,"unpack_kwargs":false,"variables":[]}}},"__iter__":{".class":"SymbolTableNode","kind":"Mdef","node":{".class":"FuncDef","abstract_status":0,"arg_kinds":[0],"arg_names":[null],"dataclass_transform_spec":null,"flags":[],"fullname":"pytorch_lightning.utilities.combined_loader.CombinedLoader.__iter__","name":"__iter__","type":{".class":"CallableType","arg_kinds":[0],"arg_names":[null],"arg_types":[{".class":"TypeVarType","fullname":"pytorch_lightning.utilities.combined_loader.CombinedLoader.Self","id":0,"name":"Self","namespace":"","upper_bound":"pytorch_lightning.utilities.combined_loader.CombinedLoader","values":[],"variance":0}],"bound_args":[],"def_extras":{"first_arg":"self"},"fallback":"builtins.function","from_concatenate":false,"implicit":false,"is_ellipsis_args":false,"name":"__iter__ of CombinedLoader","ret_type":{".class":"TypeVarType","fullname":"pytorch_lightning.utilities.combined_loader.CombinedLoader.Self","id":0,"name":"Self","namespace":"","upper_bound":"pytorch_lightning.utilities.combined_loader.CombinedLoader","values":[],"variance":0},"type_guard":null,"unpack_kwargs":false,"variables":[{".class":"TypeVarType","fullname":"pytorch_lightning.utilities.combined_loader.CombinedLoader.Self","id":0,"name":"Self","namespace":"","upper_bound":"pytorch_lightning.utilities.combined_loader.CombinedLoader","values":[],"variance":0}]}}},"__len__":{".class":"SymbolTableNode","kind":"Mdef","node":{".class":"FuncDef","abstract_status":0,"arg_kinds":[0],"arg_names":[null],"dataclass_transform_spec":null,"flags":[],"fullname":"pytorch_lightning.utilities.combined_loader.CombinedLoader.__len__","name":"__len__","type":{".class":"CallableType","arg_kinds":[0],"arg_names":[null],"arg_types":["pytorch_lightning.utilities.combined_loader.CombinedLoader"],"bound_args":[],"def_extras":{"first_arg":"self"},"fallback":"builtins.function","from_concatenate":false,"implicit":false,"is_ellipsis_args":false,"name":"__len__ of CombinedLoader","ret_type":"builtins.int","type_guard":null,"unpack_kwargs":false,"variables":[]}}},"__next__":{".class":"SymbolTableNode","kind":"Mdef","node":{".class":"FuncDef","abstract_status":0,"arg_kinds":[0],"arg_names":["self"],"dataclass_transform_spec":null,"flags":[],"fullname":"pytorch_lightning.utilities.combined_loader.CombinedLoader.__next__","name":"__next__","type":{".class":"CallableType","arg_kinds":[0],"arg_names":["self"],"arg_types":["pytorch_lightning.utilities.combined_loader.CombinedLoader"],"bound_args":[],"def_extras":{"first_arg":"self"},"fallback":"builtins.function","from_concatenate":false,"implicit":false,"is_ellipsis_args":false,"name":"__next__ of CombinedLoader","ret_type":{".class":"AnyType","missing_import_name":null,"source_any":null,"type_of_any":2},"type_guard":null,"unpack_kwargs":false,"variables":[]}}},"_dataset_length":{".class":"SymbolTableNode","kind":"Mdef","node":{".class":"FuncDef","abstract_status":0,"arg_kinds":[0],"arg_names":["self"],"dataclass_transform_spec":null,"flags":[],"fullname":"pytorch_lightning.utilities.combined_loader.CombinedLoader._dataset_length","name":"_dataset_length","type":{".class":"CallableType","arg_kinds":[0],"arg_names":["self"],"arg_types":["pytorch_lightning.utilities.combined_loader.CombinedLoader"],"bound_args":[],"def_extras":{"first_arg":"self"},"fallback":"builtins.function","from_concatenate":false,"implicit":false,"is_ellipsis_args":false,"name":"_dataset_length of CombinedLoader","ret_type":"builtins.int","type_guard":null,"unpack_kwargs":false,"variables":[]}}},"_flattened":{".class":"SymbolTableNode","implicit":true,"kind":"Mdef","node":{".class":"Var","flags":["is_inferred"],"fullname":"pytorch_lightning.utilities.combined_loader.CombinedLoader._flattened","name":"_flattened","type":{".class":"Instance","args":[{".class":"AnyType","missing_import_name":null,"source_any":null,"type_of_any":2}],"type_ref":"builtins.list"}}},"_iterables":{".class":"SymbolTableNode","implicit":true,"kind":"Mdef","node":{".class":"Var","flags":["is_inferred"],"fullname":"pytorch_lightning.utilities.combined_loader.CombinedLoader._iterables","name":"_iterables","type":{".class":"AnyType","missing_import_name":null,"source_any":null,"type_of_any":2}}},"_iterator":{".class":"SymbolTableNode","implicit":true,"kind":"Mdef","node":{".class":"Var","flags":["explicit_self_type","is_ready","is_inferred"],"fullname":"pytorch_lightning.utilities.combined_loader.CombinedLoader._iterator","name":"_iterator","type":{".class":"UnionType","items":[{".class":"Instance","args":[{".class":"AnyType","missing_import_name":null,"source_any":null,"type_of_any":4}],"type_ref":"pytorch_lightning.utilities.combined_loader._ModeIterator"},{".class":"NoneType"}]}}},"_mode":{".class":"SymbolTableNode","implicit":true,"kind":"Mdef","node":{".class":"Var","flags":["is_inferred"],"fullname":"pytorch_lightning.utilities.combined_loader.CombinedLoader._mode","name":"_mode","type":{".class":"TypeAliasType","args":[],"type_ref":"pytorch_lightning.utilities.combined_loader._LITERAL_SUPPORTED_MODES"}}},"_spec":{".class":"SymbolTableNode","implicit":true,"kind":"Mdef","node":{".class":"Var","flags":["is_inferred"],"fullname":"pytorch_lightning.utilities.combined_loader.CombinedLoader._spec","name":"_spec","type":"torch.utils._pytree.TreeSpec"}},"batch_sampler":{".class":"SymbolTableNode","kind":"Mdef","node":{".class":"Decorator","func":{".class":"FuncDef","abstract_status":0,"arg_kinds":[0],"arg_names":["self"],"dataclass_transform_spec":null,"flags":["is_property","is_decorated"],"fullname":"pytorch_lightning.utilities.combined_loader.CombinedLoader.batch_sampler","name":"batch_sampler","type":{".class":"CallableType","arg_kinds":[0],"arg_names":["self"],"arg_types":["pytorch_lightning.utilities.combined_loader.CombinedLoader"],"bound_args":[],"def_extras":{"first_arg":"self"},"fallback":"builtins.function","from_concatenate":false,"implicit":false,"is_ellipsis_args":false,"name":"batch_sampler of CombinedLoader","ret_type":{".class":"AnyType","missing_import_name":null,"source_any":null,"type_of_any":2},"type_guard":null,"unpack_kwargs":false,"variables":[]}},"is_overload":false,"var":{".class":"Var","flags":["is_initialized_in_class","is_property","is_ready","is_inferred"],"fullname":"pytorch_lightning.utilities.combined_loader.CombinedLoader.batch_sampler","name":"batch_sampler","type":{".class":"CallableType","arg_kinds":[0],"arg_names":["self"],"arg_types":["pytorch_lightning.utilities.combined_loader.CombinedLoader"],"bound_args":[],"def_extras":{"first_arg":"self"},"fallback":"builtins.function","from_concatenate":false,"implicit":false,"is_ellipsis_args":false,"name":"batch_sampler of CombinedLoader","ret_type":{".class":"AnyType","missing_import_name":null,"source_any":null,"type_of_any":2},"type_guard":null,"unpack_kwargs":false,"variables":[]}}}},"flattened":{".class":"SymbolTableNode","kind":"Mdef","node":{".class":"OverloadedFuncDef","flags":["is_property"],"fullname":"pytorch_lightning.utilities.combined_loader.CombinedLoader.flattened","impl":null,"items":[{".class":"Decorator","func":{".class":"FuncDef","abstract_status":0,"arg_kinds":[0],"arg_names":["self"],"dataclass_transform_spec":null,"flags":["is_property","is_overload","is_decorated"],"fullname":"pytorch_lightning.utilities.combined_loader.CombinedLoader.flattened","name":"flattened","type":{".class":"CallableType","arg_kinds":[0],"arg_names":["self"],"arg_types":["pytorch_lightning.utilities.combined_loader.CombinedLoader"],"bound_args":[],"def_extras":{"first_arg":"self"},"fallback":"builtins.function","from_concatenate":false,"implicit":false,"is_ellipsis_args":false,"name":"flattened of CombinedLoader","ret_type":{".class":"Instance","args":[{".class":"AnyType","missing_import_name":null,"source_any":null,"type_of_any":2}],"type_ref":"builtins.list"},"type_guard":null,"unpack_kwargs":false,"variables":[]}},"is_overload":true,"var":{".class":"Var","flags":["is_initialized_in_class","is_property","is_settable_property","is_ready","is_inferred"],"fullname":"pytorch_lightning.utilities.combined_loader.CombinedLoader.flattened","name":"flattened","type":{".class":"CallableType","arg_kinds":[0],"arg_names":["self"],"arg_types":["pytorch_lightning.utilities.combined_loader.CombinedLoader"],"bound_args":[],"def_extras":{"first_arg":"self"},"fallback":"builtins.function","from_concatenate":false,"implicit":false,"is_ellipsis_args":false,"name":"flattened of CombinedLoader","ret_type":{".class":"Instance","args":[{".class":"AnyType","missing_import_name":null,"source_any":null,"type_of_any":2}],"type_ref":"builtins.list"},"type_guard":null,"unpack_kwargs":false,"variables":[]}}},{".class":"Decorator","func":{".class":"FuncDef","abstract_status":0,"arg_kinds":[0,0],"arg_names":["self","flattened"],"dataclass_transform_spec":null,"flags":["is_decorated"],"fullname":"pytorch_lightning.utilities.combined_loader.CombinedLoader.flattened","name":"flattened","type":{".class":"CallableType","arg_kinds":[0,0],"arg_names":["self","flattened"],"arg_types":["pytorch_lightning.utilities.combined_loader.CombinedLoader",{".class":"Instance","args":[{".class":"AnyType","missing_import_name":null,"source_any":null,"type_of_any":2}],"type_ref":"builtins.list"}],"bound_args":[],"def_extras":{"first_arg":"self"},"fallback":"builtins.function","from_concatenate":false,"implicit":false,"is_ellipsis_args":false,"name":"flattened of CombinedLoader","ret_type":{".class":"NoneType"},"type_guard":null,"unpack_kwargs":false,"variables":[]}},"is_overload":false,"var":{".class":"Var","flags":["is_inferred"],"fullname":"","name":"flattened","type":null}}],"type":{".class":"Overloaded","items":[{".class":"CallableType","arg_kinds":[0],"arg_names":["self"],"arg_types":["pytorch_lightning.utilities.combined_loader.CombinedLoader"],"bound_args":[],"def_extras":{"first_arg":"self"},"fallback":"builtins.function","from_concatenate":false,"implicit":false,"is_ellipsis_args":false,"name":"flattened of CombinedLoader","ret_type":{".class":"Instance","args":[{".class":"AnyType","missing_import_name":null,"source_any":null,"type_of_any":2}],"type_ref":"builtins.list"},"type_guard":null,"unpack_kwargs":false,"variables":[]}]}}},"iterables":{".class":"SymbolTableNode","kind":"Mdef","node":{".class":"Decorator","func":{".class":"FuncDef","abstract_status":0,"arg_kinds":[0],"arg_names":["self"],"dataclass_transform_spec":null,"flags":["is_property","is_decorated"],"fullname":"pytorch_lightning.utilities.combined_loader.CombinedLoader.iterables","name":"iterables","type":{".class":"CallableType","arg_kinds":[0],"arg_names":["self"],"arg_types":["pytorch_lightning.utilities.combined_loader.CombinedLoader"],"bound_args":[],"def_extras":{"first_arg":"self"},"fallback":"builtins.function","from_concatenate":false,"implicit":false,"is_ellipsis_args":false,"name":"iterables of CombinedLoader","ret_type":{".class":"AnyType","missing_import_name":null,"source_any":null,"type_of_any":2},"type_guard":null,"unpack_kwargs":false,"variables":[]}},"is_overload":false,"var":{".class":"Var","flags":["is_initialized_in_class","is_property","is_ready","is_inferred"],"fullname":"pytorch_lightning.utilities.combined_loader.CombinedLoader.iterables","name":"iterables","type":{".class":"CallableType","arg_kinds":[0],"arg_names":["self"],"arg_types":["pytorch_lightning.utilities.combined_loader.CombinedLoader"],"bound_args":[],"def_extras":{"first_arg":"self"},"fallback":"builtins.function","from_concatenate":false,"implicit":false,"is_ellipsis_args":false,"name":"iterables of CombinedLoader","ret_type":{".class":"AnyType","missing_import_name":null,"source_any":null,"type_of_any":2},"type_guard":null,"unpack_kwargs":false,"variables":[]}}}},"reset":{".class":"SymbolTableNode","kind":"Mdef","node":{".class":"FuncDef","abstract_status":0,"arg_kinds":[0],"arg_names":["self"],"dataclass_transform_spec":null,"flags":[],"fullname":"pytorch_lightning.utilities.combined_loader.CombinedLoader.reset","name":"reset","type":{".class":"CallableType","arg_kinds":[0],"arg_names":["self"],"arg_types":["pytorch_lightning.utilities.combined_loader.CombinedLoader"],"bound_args":[],"def_extras":{"first_arg":"self"},"fallback":"builtins.function","from_concatenate":false,"implicit":false,"is_ellipsis_args":false,"name":"reset of CombinedLoader","ret_type":{".class":"NoneType"},"type_guard":null,"unpack_kwargs":false,"variables":[]}}},"sampler":{".class":"SymbolTableNode","kind":"Mdef","node":{".class":"Decorator","func":{".class":"FuncDef","abstract_status":0,"arg_kinds":[0],"arg_names":["self"],"dataclass_transform_spec":null,"flags":["is_property","is_decorated"],"fullname":"pytorch_lightning.utilities.combined_loader.CombinedLoader.sampler","name":"sampler","type":{".class":"CallableType","arg_kinds":[0],"arg_names":["self"],"arg_types":["pytorch_lightning.utilities.combined_loader.CombinedLoader"],"bound_args":[],"def_extras":{"first_arg":"self"},"fallback":"builtins.function","from_concatenate":false,"implicit":false,"is_ellipsis_args":false,"name":"sampler of CombinedLoader","ret_type":{".class":"AnyType","missing_import_name":null,"source_any":null,"type_of_any":2},"type_guard":null,"unpack_kwargs":false,"variables":[]}},"is_overload":false,"var":{".class":"Var","flags":["is_initialized_in_class","is_property","is_ready","is_inferred"],"fullname":"pytorch_lightning.utilities.combined_loader.CombinedLoader.sampler","name":"sampler","type":{".class":"CallableType","arg_kinds":[0],"arg_names":["self"],"arg_types":["pytorch_lightning.utilities.combined_loader.CombinedLoader"],"bound_args":[],"def_extras":{"first_arg":"self"},"fallback":"builtins.function","from_concatenate":false,"implicit":false,"is_ellipsis_args":false,"name":"sampler of CombinedLoader","ret_type":{".class":"AnyType","missing_import_name":null,"source_any":null,"type_of_any":2},"type_guard":null,"unpack_kwargs":false,"variables":[]}}}}},"self_type":{".class":"TypeVarType","fullname":"pytorch_lightning.utilities.combined_loader.CombinedLoader.Self","id":0,"name":"Self","namespace":"","upper_bound":"pytorch_lightning.utilities.combined_loader.CombinedLoader","values":[],"variance":0},"slots":null,"tuple_type":null,"type_vars":[],"typeddict_type":null}},"Dict":{".class":"SymbolTableNode","cross_ref":"typing.Dict","kind":"Gdef"},"Iterable":{".class":"SymbolTableNode","cross_ref":"typing.Iterable","kind":"Gdef"},"Iterator":{".class":"SymbolTableNode","cross_ref":"typing.Iterator","kind":"Gdef"},"List":{".class":"SymbolTableNode","cross_ref":"typing.List","kind":"Gdef"},"Literal":{".class":"SymbolTableNode","cross_ref":"typing.Literal","kind":"Gdef"},"Optional":{".class":"SymbolTableNode","cross_ref":"typing.Optional","kind":"Gdef"},"Self":{".class":"SymbolTableNode","cross_ref":"typing_extensions.Self","kind":"Gdef"},"Tuple":{".class":"SymbolTableNode","cross_ref":"typing.Tuple","kind":"Gdef"},"Type":{".class":"SymbolTableNode","cross_ref":"typing.Type","kind":"Gdef"},"TypeVar":{".class":"SymbolTableNode","cross_ref":"typing.TypeVar","kind":"Gdef"},"TypedDict":{".class":"SymbolTableNode","cross_ref":"typing_extensions.TypedDict","kind":"Gdef"},"Union":{".class":"SymbolTableNode","cross_ref":"typing.Union","kind":"Gdef"},"_BaseDataLoaderIter":{".class":"SymbolTableNode","cross_ref":"torch.utils.data.dataloader._BaseDataLoaderIter","kind":"Gdef"},"_CombinationMode":{".class":"SymbolTableNode","kind":"Gdef","node":{".class":"TypeInfo","_promote":[],"abstract_attributes":[],"alt_promote":null,"bases":["typing._TypedDict"],"dataclass_transform_spec":null,"declared_metaclass":null,"defn":{".class":"ClassDef","fullname":"pytorch_lightning.utilities.combined_loader._CombinationMode","name":"_CombinationMode","type_vars":[]},"deletable_attributes":[],"flags":[],"fullname":"pytorch_lightning.utilities.combined_loader._CombinationMode","has_param_spec_type":false,"metaclass_type":null,"metadata":{},"module_name":"pytorch_lightning.utilities.combined_loader","mro":["pytorch_lightning.utilities.combined_loader._CombinationMode","typing._TypedDict","typing.Mapping","typing.Collection","typing.Iterable","typing.Container","builtins.object"],"names":{".class":"SymbolTable"},"self_type":null,"slots":null,"tuple_type":null,"type_vars":[],"typeddict_type":{".class":"TypedDictType","fallback":"typing._TypedDict","items":[["fn",{".class":"CallableType","arg_kinds":[0],"arg_names":[null],"arg_types":[{".class":"Instance","args":["builtins.int"],"type_ref":"builtins.list"}],"bound_args":[],"def_extras":{},"fallback":"builtins.function","from_concatenate":false,"implicit":false,"is_ellipsis_args":false,"name":null,"ret_type":"builtins.int","type_guard":null,"unpack_kwargs":false,"variables":[]}],["iterator",{".class":"TypeType","item":{".class":"Instance","args":[{".class":"AnyType","missing_import_name":null,"source_any":null,"type_of_any":4}],"type_ref":"pytorch_lightning.utilities.combined_loader._ModeIterator"}}]],"required_keys":["fn","iterator"]}}},"_LITERAL_SUPPORTED_MODES":{".class":"SymbolTableNode","kind":"Gdef","node":{".class":"TypeAlias","alias_tvars":[],"column":0,"fullname":"pytorch_lightning.utilities.combined_loader._LITERAL_SUPPORTED_MODES","line":175,"no_args":false,"normalized":false,"target":{".class":"UnionType","items":[{".class":"LiteralType","fallback":"builtins.str","value":"min_size"},{".class":"LiteralType","fallback":"builtins.str","value":"max_size_cycle"},{".class":"LiteralType","fallback":"builtins.str","value":"max_size"},{".class":"LiteralType","fallback":"builtins.str","value":"sequential"}]}}},"_MaxSize":{".class":"SymbolTableNode","kind":"Gdef","node":{".class":"TypeInfo","_promote":[],"abstract_attributes":[],"alt_promote":null,"bases":[{".class":"Instance","args":[{".class":"Instance","args":[{".class":"AnyType","missing_import_name":null,"source_any":null,"type_of_any":4}],"type_ref":"builtins.list"}],"type_ref":"pytorch_lightning.utilities.combined_loader._ModeIterator"}],"dataclass_transform_spec":null,"declared_metaclass":null,"defn":{".class":"ClassDef","fullname":"pytorch_lightning.utilities.combined_loader._MaxSize","name":"_MaxSize","type_vars":[]},"deletable_attributes":[],"flags":[],"fullname":"pytorch_lightning.utilities.combined_loader._MaxSize","has_param_spec_type":false,"metaclass_type":"abc.ABCMeta","metadata":{},"module_name":"pytorch_lightning.utilities.combined_loader","mro":["pytorch_lightning.utilities.combined_loader._MaxSize","pytorch_lightning.utilities.combined_loader._ModeIterator","typing.Iterator","typing.Iterable","builtins.object"],"names":{".class":"SymbolTable","__next__":{".class":"SymbolTableNode","kind":"Mdef","node":{".class":"FuncDef","abstract_status":0,"arg_kinds":[0],"arg_names":["self"],"dataclass_transform_spec":null,"flags":[],"fullname":"pytorch_lightning.utilities.combined_loader._MaxSize.__next__","name":"__next__","type":{".class":"CallableType","arg_kinds":[0],"arg_names":["self"],"arg_types":["pytorch_lightning.utilities.combined_loader._MaxSize"],"bound_args":[],"def_extras":{"first_arg":"self"},"fallback":"builtins.function","from_concatenate":false,"implicit":false,"is_ellipsis_args":false,"name":"__next__ of _MaxSize","ret_type":{".class":"Instance","args":[{".class":"AnyType","missing_import_name":null,"source_any":null,"type_of_any":4}],"type_ref":"builtins.list"},"type_guard":null,"unpack_kwargs":false,"variables":[]}}}},"self_type":null,"slots":null,"tuple_type":null,"type_vars":[],"typeddict_type":null}},"_MaxSizeCycle":{".class":"SymbolTableNode","kind":"Gdef","node":{".class":"TypeInfo","_promote":[],"abstract_attributes":[],"alt_promote":null,"bases":[{".class":"Instance","args":[{".class":"Instance","args":[{".class":"AnyType","missing_import_name":null,"source_any":null,"type_of_any":4}],"type_ref":"builtins.list"}],"type_ref":"pytorch_lightning.utilities.combined_loader._ModeIterator"}],"dataclass_transform_spec":null,"declared_metaclass":null,"defn":{".class":"ClassDef","fullname":"pytorch_lightning.utilities.combined_loader._MaxSizeCycle","name":"_MaxSizeCycle","type_vars":[]},"deletable_attributes":[],"flags":[],"fullname":"pytorch_lightning.utilities.combined_loader._MaxSizeCycle","has_param_spec_type":false,"metaclass_type":"abc.ABCMeta","metadata":{},"module_name":"pytorch_lightning.utilities.combined_loader","mro":["pytorch_lightning.utilities.combined_loader._MaxSizeCycle","pytorch_lightning.utilities.combined_loader._ModeIterator","typing.Iterator","typing.Iterable","builtins.object"],"names":{".class":"SymbolTable","__init__":{".class":"SymbolTableNode","kind":"Mdef","node":{".class":"FuncDef","abstract_status":0,"arg_kinds":[0,0],"arg_names":["self","iterables"],"dataclass_transform_spec":null,"flags":[],"fullname":"pytorch_lightning.utilities.combined_loader._MaxSizeCycle.__init__","name":"__init__","type":{".class":"CallableType","arg_kinds":[0,0],"arg_names":["self","iterables"],"arg_types":["pytorch_lightning.utilities.combined_loader._MaxSizeCycle",{".class":"Instance","args":[{".class":"Instance","args":[{".class":"AnyType","missing_import_name":null,"source_any":null,"type_of_any":4}],"type_ref":"typing.Iterable"}],"type_ref":"builtins.list"}],"bound_args":[],"def_extras":{"first_arg":"self"},"fallback":"builtins.function","from_concatenate":false,"implicit":false,"is_ellipsis_args":false,"name":"__init__ of _MaxSizeCycle","ret_type":{".class":"NoneType"},"type_guard":null,"unpack_kwargs":false,"variables":[]}}},"__iter__":{".class":"SymbolTableNode","kind":"Mdef","node":{".class":"FuncDef","abstract_status":0,"arg_kinds":[0],"arg_names":[null],"dataclass_transform_spec":null,"flags":[],"fullname":"pytorch_lightning.utilities.combined_loader._MaxSizeCycle.__iter__","name":"__iter__","type":{".class":"CallableType","arg_kinds":[0],"arg_names":[null],"arg_types":[{".class":"TypeVarType","fullname":"pytorch_lightning.utilities.combined_loader._MaxSizeCycle.Self","id":0,"name":"Self","namespace":"","upper_bound":"pytorch_lightning.utilities.combined_loader._MaxSizeCycle","values":[],"variance":0}],"bound_args":[],"def_extras":{"first_arg":"self"},"fallback":"builtins.function","from_concatenate":false,"implicit":false,"is_ellipsis_args":false,"name":"__iter__ of _MaxSizeCycle","ret_type":{".class":"TypeVarType","fullname":"pytorch_lightning.utilities.combined_loader._MaxSizeCycle.Self","id":0,"name":"Self","namespace":"","upper_bound":"pytorch_lightning.utilities.combined_loader._MaxSizeCycle","values":[],"variance":0},"type_guard":null,"unpack_kwargs":false,"variables":[{".class":"TypeVarType","fullname":"pytorch_lightning.utilities.combined_loader._MaxSizeCycle.Self","id":0,"name":"Self","namespace":"","upper_bound":"pytorch_lightning.utilities.combined_loader._MaxSizeCycle","values":[],"variance":0}]}}},"__next__":{".class":"SymbolTableNode","kind":"Mdef","node":{".class":"FuncDef","abstract_status":0,"arg_kinds":[0],"arg_names":["self"],"dataclass_transform_spec":null,"flags":[],"fullname":"pytorch_lightning.utilities.combined_loader._MaxSizeCycle.__next__","name":"__next__","type":{".class":"CallableType","arg_kinds":[0],"arg_names":["self"],"arg_types":["pytorch_lightning.utilities.combined_loader._MaxSizeCycle"],"bound_args":[],"def_extras":{"first_arg":"self"},"fallback":"builtins.function","from_concatenate":false,"implicit":false,"is_ellipsis_args":false,"name":"__next__ of _MaxSizeCycle","ret_type":{".class":"Instance","args":[{".class":"AnyType","missing_import_name":null,"source_any":null,"type_of_any":4}],"type_ref":"builtins.list"},"type_guard":null,"unpack_kwargs":false,"variables":[]}}},"_consumed":{".class":"SymbolTableNode","implicit":true,"kind":"Mdef","node":{".class":"Var","flags":["explicit_self_type","is_ready","is_inferred"],"fullname":"pytorch_lightning.utilities.combined_loader._MaxSizeCycle._consumed","name":"_consumed","type":{".class":"Instance","args":["builtins.bool"],"type_ref":"builtins.list"}}},"reset":{".class":"SymbolTableNode","kind":"Mdef","node":{".class":"FuncDef","abstract_status":0,"arg_kinds":[0],"arg_names":["self"],"dataclass_transform_spec":null,"flags":[],"fullname":"pytorch_lightning.utilities.combined_loader._MaxSizeCycle.reset","name":"reset","type":{".class":"CallableType","arg_kinds":[0],"arg_names":["self"],"arg_types":["pytorch_lightning.utilities.combined_loader._MaxSizeCycle"],"bound_args":[],"def_extras":{"first_arg":"self"},"fallback":"builtins.function","from_concatenate":false,"implicit":false,"is_ellipsis_args":false,"name":"reset of _MaxSizeCycle","ret_type":{".class":"NoneType"},"type_guard":null,"unpack_kwargs":false,"variables":[]}}}},"self_type":{".class":"TypeVarType","fullname":"pytorch_lightning.utilities.combined_loader._MaxSizeCycle.Self","id":0,"name":"Self","namespace":"","upper_bound":"pytorch_lightning.utilities.combined_loader._MaxSizeCycle","values":[],"variance":0},"slots":null,"tuple_type":null,"type_vars":[],"typeddict_type":null}},"_MinSize":{".class":"SymbolTableNode","kind":"Gdef","node":{".class":"TypeInfo","_promote":[],"abstract_attributes":[],"alt_promote":null,"bases":[{".class":"Instance","args":[{".class":"Instance","args":[{".class":"AnyType","missing_import_name":null,"source_any":null,"type_of_any":4}],"type_ref":"builtins.list"}],"type_ref":"pytorch_lightning.utilities.combined_loader._ModeIterator"}],"dataclass_transform_spec":null,"declared_metaclass":null,"defn":{".class":"ClassDef","fullname":"pytorch_lightning.utilities.combined_loader._MinSize","name":"_MinSize","type_vars":[]},"deletable_attributes":[],"flags":[],"fullname":"pytorch_lightning.utilities.combined_loader._MinSize","has_param_spec_type":false,"metaclass_type":"abc.ABCMeta","metadata":{},"module_name":"pytorch_lightning.utilities.combined_loader","mro":["pytorch_lightning.utilities.combined_loader._MinSize","pytorch_lightning.utilities.combined_loader._ModeIterator","typing.Iterator","typing.Iterable","builtins.object"],"names":{".class":"SymbolTable","__next__":{".class":"SymbolTableNode","kind":"Mdef","node":{".class":"FuncDef","abstract_status":0,"arg_kinds":[0],"arg_names":["self"],"dataclass_transform_spec":null,"flags":[],"fullname":"pytorch_lightning.utilities.combined_loader._MinSize.__next__","name":"__next__","type":{".class":"CallableType","arg_kinds":[0],"arg_names":["self"],"arg_types":["pytorch_lightning.utilities.combined_loader._MinSize"],"bound_args":[],"def_extras":{"first_arg":"self"},"fallback":"builtins.function","from_concatenate":false,"implicit":false,"is_ellipsis_args":false,"name":"__next__ of _MinSize","ret_type":{".class":"Instance","args":[{".class":"AnyType","missing_import_name":null,"source_any":null,"type_of_any":4}],"type_ref":"builtins.list"},"type_guard":null,"unpack_kwargs":false,"variables":[]}}}},"self_type":null,"slots":null,"tuple_type":null,"type_vars":[],"typeddict_type":null}},"_ModeIterator":{".class":"SymbolTableNode","kind":"Gdef","node":{".class":"TypeInfo","_promote":[],"abstract_attributes":[],"alt_promote":null,"bases":[{".class":"Instance","args":[{".class":"TypeVarType","fullname":"pytorch_lightning.utilities.combined_loader._T","id":1,"name":"_T","namespace":"pytorch_lightning.utilities.combined_loader._ModeIterator","upper_bound":"builtins.object","values":[],"variance":0}],"type_ref":"typing.Iterator"}],"dataclass_transform_spec":null,"declared_metaclass":null,"defn":{".class":"ClassDef","fullname":"pytorch_lightning.utilities.combined_loader._ModeIterator","name":"_ModeIterator","type_vars":[{".class":"TypeVarType","fullname":"pytorch_lightning.utilities.combined_loader._T","id":1,"name":"_T","namespace":"pytorch_lightning.utilities.combined_loader._ModeIterator","upper_bound":"builtins.object","values":[],"variance":0}]},"deletable_attributes":[],"flags":[],"fullname":"pytorch_lightning.utilities.combined_loader._ModeIterator","has_param_spec_type":false,"metaclass_type":"abc.ABCMeta","metadata":{},"module_name":"pytorch_lightning.utilities.combined_loader","mro":["pytorch_lightning.utilities.combined_loader._ModeIterator","typing.Iterator","typing.Iterable","builtins.object"],"names":{".class":"SymbolTable","__getstate__":{".class":"SymbolTableNode","kind":"Mdef","node":{".class":"FuncDef","abstract_status":0,"arg_kinds":[0],"arg_names":["self"],"dataclass_transform_spec":null,"flags":[],"fullname":"pytorch_lightning.utilities.combined_loader._ModeIterator.__getstate__","name":"__getstate__","type":{".class":"CallableType","arg_kinds":[0],"arg_names":["self"],"arg_types":[{".class":"Instance","args":[{".class":"TypeVarType","fullname":"pytorch_lightning.utilities.combined_loader._T","id":1,"name":"_T","namespace":"pytorch_lightning.utilities.combined_loader._ModeIterator","upper_bound":"builtins.object","values":[],"variance":0}],"type_ref":"pytorch_lightning.utilities.combined_loader._ModeIterator"}],"bound_args":[],"def_extras":{"first_arg":"self"},"fallback":"builtins.function","from_concatenate":false,"implicit":false,"is_ellipsis_args":false,"name":"__getstate__ of _ModeIterator","ret_type":{".class":"Instance","args":["builtins.str",{".class":"AnyType","missing_import_name":null,"source_any":null,"type_of_any":2}],"type_ref":"builtins.dict"},"type_guard":null,"unpack_kwargs":false,"variables":[]}}},"__init__":{".class":"SymbolTableNode","kind":"Mdef","node":{".class":"FuncDef","abstract_status":0,"arg_kinds":[0,0],"arg_names":["self","iterables"],"dataclass_transform_spec":null,"flags":[],"fullname":"pytorch_lightning.utilities.combined_loader._ModeIterator.__init__","name":"__init__","type":{".class":"CallableType","arg_kinds":[0,0],"arg_names":["self","iterables"],"arg_types":[{".class":"Instance","args":[{".class":"TypeVarType","fullname":"pytorch_lightning.utilities.combined_loader._T","id":1,"name":"_T","namespace":"pytorch_lightning.utilities.combined_loader._ModeIterator","upper_bound":"builtins.object","values":[],"variance":0}],"type_ref":"pytorch_lightning.utilities.combined_loader._ModeIterator"},{".class":"Instance","args":[{".class":"Instance","args":[{".class":"AnyType","missing_import_name":null,"source_any":null,"type_of_any":4}],"type_ref":"typing.Iterable"}],"type_ref":"builtins.list"}],"bound_args":[],"def_extras":{"first_arg":"self"},"fallback":"builtins.function","from_concatenate":false,"implicit":false,"is_ellipsis_args":false,"name":"__init__ of _ModeIterator","ret_type":{".class":"NoneType"},"type_guard":null,"unpack_kwargs":false,"variables":[]}}},"__iter__":{".class":"SymbolTableNode","kind":"Mdef","node":{".class":"FuncDef","abstract_status":0,"arg_kinds":[0],"arg_names":[null],"dataclass_transform_spec":null,"flags":[],"fullname":"pytorch_lightning.utilities.combined_loader._ModeIterator.__iter__","name":"__iter__","type":{".class":"CallableType","arg_kinds":[0],"arg_names":[null],"arg_types":[{".class":"TypeVarType","fullname":"pytorch_lightning.utilities.combined_loader._ModeIterator.Self","id":0,"name":"Self","namespace":"","upper_bound":{".class":"Instance","args":[{".class":"TypeVarType","fullname":"pytorch_lightning.utilities.combined_loader._T","id":1,"name":"_T","namespace":"pytorch_lightning.utilities.combined_loader._ModeIterator","upper_bound":"builtins.object","values":[],"variance":0}],"type_ref":"pytorch_lightning.utilities.combined_loader._ModeIterator"},"values":[],"variance":0}],"bound_args":[],"def_extras":{"first_arg":"self"},"fallback":"builtins.function","from_concatenate":false,"implicit":false,"is_ellipsis_args":false,"name":"__iter__ of _ModeIterator","ret_type":{".class":"TypeVarType","fullname":"pytorch_lightning.utilities.combined_loader._ModeIterator.Self","id":0,"name":"Self","namespace":"","upper_bound":{".class":"Instance","args":[{".class":"TypeVarType","fullname":"pytorch_lightning.utilities.combined_loader._T","id":1,"name":"_T","namespace":"pytorch_lightning.utilities.combined_loader._ModeIterator","upper_bound":"builtins.object","values":[],"variance":0}],"type_ref":"pytorch_lightning.utilities.combined_loader._ModeIterator"},"values":[],"variance":0},"type_guard":null,"unpack_kwargs":false,"variables":[{".class":"TypeVarType","fullname":"pytorch_lightning.utilities.combined_loader._ModeIterator.Self","id":0,"name":"Self","namespace":"","upper_bound":{".class":"Instance","args":[{".class":"TypeVarType","fullname":"pytorch_lightning.utilities.combined_loader._T","id":1,"name":"_T","namespace":"pytorch_lightning.utilities.combined_loader._ModeIterator","upper_bound":"builtins.object","values":[],"variance":0}],"type_ref":"pytorch_lightning.utilities.combined_loader._ModeIterator"},"values":[],"variance":0}]}}},"__next__":{".class":"SymbolTableNode","kind":"Mdef","node":{".class":"FuncDef","abstract_status":0,"arg_kinds":[0],"arg_names":["self"],"dataclass_transform_spec":null,"flags":[],"fullname":"pytorch_lightning.utilities.combined_loader._ModeIterator.__next__","name":"__next__","type":{".class":"CallableType","arg_kinds":[0],"arg_names":["self"],"arg_types":[{".class":"Instance","args":[{".class":"TypeVarType","fullname":"pytorch_lightning.utilities.combined_loader._T","id":1,"name":"_T","namespace":"pytorch_lightning.utilities.combined_loader._ModeIterator","upper_bound":"builtins.object","values":[],"variance":0}],"type_ref":"pytorch_lightning.utilities.combined_loader._ModeIterator"}],"bound_args":[],"def_extras":{"first_arg":"self"},"fallback":"builtins.function","from_concatenate":false,"implicit":false,"is_ellipsis_args":false,"name":"__next__ of _ModeIterator","ret_type":{".class":"TypeVarType","fullname":"pytorch_lightning.utilities.combined_loader._T","id":1,"name":"_T","namespace":"pytorch_lightning.utilities.combined_loader._ModeIterator","upper_bound":"builtins.object","values":[],"variance":0},"type_guard":null,"unpack_kwargs":false,"variables":[]}}},"iterables":{".class":"SymbolTableNode","implicit":true,"kind":"Mdef","node":{".class":"Var","flags":["is_inferred"],"fullname":"pytorch_lightning.utilities.combined_loader._ModeIterator.iterables","name":"iterables","type":{".class":"Instance","args":[{".class":"Instance","args":[{".class":"AnyType","missing_import_name":null,"source_any":null,"type_of_any":4}],"type_ref":"typing.Iterable"}],"type_ref":"builtins.list"}}},"iterators":{".class":"SymbolTableNode","implicit":true,"kind":"Mdef","node":{".class":"Var","flags":["explicit_self_type","is_ready","is_inferred"],"fullname":"pytorch_lightning.utilities.combined_loader._ModeIterator.iterators","name":"iterators","type":{".class":"Instance","args":[{".class":"Instance","args":[{".class":"AnyType","missing_import_name":null,"source_any":null,"type_of_any":4}],"type_ref":"typing.Iterator"}],"type_ref":"builtins.list"}}},"reset":{".class":"SymbolTableNode","kind":"Mdef","node":{".class":"FuncDef","abstract_status":0,"arg_kinds":[0],"arg_names":["self"],"dataclass_transform_spec":null,"flags":[],"fullname":"pytorch_lightning.utilities.combined_loader._ModeIterator.reset","name":"reset","type":{".class":"CallableType","arg_kinds":[0],"arg_names":["self"],"arg_types":[{".class":"Instance","args":[{".class":"TypeVarType","fullname":"pytorch_lightning.utilities.combined_loader._T","id":1,"name":"_T","namespace":"pytorch_lightning.utilities.combined_loader._ModeIterator","upper_bound":"builtins.object","values":[],"variance":0}],"type_ref":"pytorch_lightning.utilities.combined_loader._ModeIterator"}],"bound_args":[],"def_extras":{"first_arg":"self"},"fallback":"builtins.function","from_concatenate":false,"implicit":false,"is_ellipsis_args":false,"name":"reset of _ModeIterator","ret_type":{".class":"NoneType"},"type_guard":null,"unpack_kwargs":false,"variables":[]}}}},"self_type":{".class":"TypeVarType","fullname":"pytorch_lightning.utilities.combined_loader._ModeIterator.Self","id":0,"name":"Self","namespace":"","upper_bound":{".class":"Instance","args":[{".class":"TypeVarType","fullname":"pytorch_lightning.utilities.combined_loader._T","id":1,"name":"_T","namespace":"pytorch_lightning.utilities.combined_loader._ModeIterator","upper_bound":"builtins.object","values":[],"variance":0}],"type_ref":"pytorch_lightning.utilities.combined_loader._ModeIterator"},"values":[],"variance":0},"slots":null,"tuple_type":null,"type_vars":["_T"],"typeddict_type":null}},"_MultiProcessingDataLoaderIter":{".class":"SymbolTableNode","cross_ref":"torch.utils.data.dataloader._MultiProcessingDataLoaderIter","kind":"Gdef"},"_SUPPORTED_MODES":{".class":"SymbolTableNode","kind":"Gdef","node":{".class":"Var","flags":["is_inferred","has_explicit_value"],"fullname":"pytorch_lightning.utilities.combined_loader._SUPPORTED_MODES","name":"_SUPPORTED_MODES","type":{".class":"Instance","args":["builtins.str",{".class":"TypedDictType","fallback":"typing._TypedDict","items":[["fn",{".class":"CallableType","arg_kinds":[0],"arg_names":[null],"arg_types":[{".class":"Instance","args":["builtins.int"],"type_ref":"builtins.list"}],"bound_args":[],"def_extras":{},"fallback":"builtins.function","from_concatenate":false,"implicit":false,"is_ellipsis_args":false,"name":null,"ret_type":"builtins.int","type_guard":null,"unpack_kwargs":false,"variables":[]}],["iterator",{".class":"TypeType","item":{".class":"Instance","args":[{".class":"AnyType","missing_import_name":null,"source_any":null,"type_of_any":4}],"type_ref":"pytorch_lightning.utilities.combined_loader._ModeIterator"}}]],"required_keys":["fn","iterator"]}],"type_ref":"builtins.dict"}}},"_Sequential":{".class":"SymbolTableNode","kind":"Gdef","node":{".class":"TypeInfo","_promote":[],"abstract_attributes":[],"alt_promote":null,"bases":[{".class":"Instance","args":[{".class":"TupleType","implicit":false,"items":[{".class":"AnyType","missing_import_name":null,"source_any":null,"type_of_any":2},"builtins.int","builtins.int"],"partial_fallback":{".class":"Instance","args":[{".class":"AnyType","missing_import_name":null,"source_any":null,"type_of_any":6}],"type_ref":"builtins.tuple"}}],"type_ref":"pytorch_lightning.utilities.combined_loader._ModeIterator"}],"dataclass_transform_spec":null,"declared_metaclass":null,"defn":{".class":"ClassDef","fullname":"pytorch_lightning.utilities.combined_loader._Sequential","name":"_Sequential","type_vars":[]},"deletable_attributes":[],"flags":[],"fullname":"pytorch_lightning.utilities.combined_loader._Sequential","has_param_spec_type":false,"metaclass_type":"abc.ABCMeta","metadata":{},"module_name":"pytorch_lightning.utilities.combined_loader","mro":["pytorch_lightning.utilities.combined_loader._Sequential","pytorch_lightning.utilities.combined_loader._ModeIterator","typing.Iterator","typing.Iterable","builtins.object"],"names":{".class":"SymbolTable","__init__":{".class":"SymbolTableNode","kind":"Mdef","node":{".class":"FuncDef","abstract_status":0,"arg_kinds":[0,0,1],"arg_names":["self","iterables","limits"],"dataclass_transform_spec":null,"flags":[],"fullname":"pytorch_lightning.utilities.combined_loader._Sequential.__init__","name":"__init__","type":{".class":"CallableType","arg_kinds":[0,0,1],"arg_names":["self","iterables","limits"],"arg_types":["pytorch_lightning.utilities.combined_loader._Sequential",{".class":"Instance","args":[{".class":"Instance","args":[{".class":"AnyType","missing_import_name":null,"source_any":null,"type_of_any":4}],"type_ref":"typing.Iterable"}],"type_ref":"builtins.list"},{".class":"UnionType","items":[{".class":"Instance","args":[{".class":"UnionType","items":["builtins.int","builtins.float"]}],"type_ref":"builtins.list"},{".class":"NoneType"}]}],"bound_args":[],"def_extras":{"first_arg":"self"},"fallback":"builtins.function","from_concatenate":false,"implicit":false,"is_ellipsis_args":false,"name":"__init__ of _Sequential","ret_type":{".class":"NoneType"},"type_guard":null,"unpack_kwargs":false,"variables":[]}}},"__iter__":{".class":"SymbolTableNode","kind":"Mdef","node":{".class":"FuncDef","abstract_status":0,"arg_kinds":[0],"arg_names":[null],"dataclass_transform_spec":null,"flags":[],"fullname":"pytorch_lightning.utilities.combined_loader._Sequential.__iter__","name":"__iter__","type":{".class":"CallableType","arg_kinds":[0],"arg_names":[null],"arg_types":[{".class":"TypeVarType","fullname":"pytorch_lightning.utilities.combined_loader._Sequential.Self","id":0,"name":"Self","namespace":"","upper_bound":"pytorch_lightning.utilities.combined_loader._Sequential","values":[],"variance":0}],"bound_args":[],"def_extras":{"first_arg":"self"},"fallback":"builtins.function","from_concatenate":false,"implicit":false,"is_ellipsis_args":false,"name":"__iter__ of _Sequential","ret_type":{".class":"TypeVarType","fullname":"pytorch_lightning.utilities.combined_loader._Sequential.Self","id":0,"name":"Self","namespace":"","upper_bound":"pytorch_lightning.utilities.combined_loader._Sequential","values":[],"variance":0},"type_guard":null,"unpack_kwargs":false,"variables":[{".class":"TypeVarType","fullname":"pytorch_lightning.utilities.combined_loader._Sequential.Self","id":0,"name":"Self","namespace":"","upper_bound":"pytorch_lightning.utilities.combined_loader._Sequential","values":[],"variance":0}]}}},"__next__":{".class":"SymbolTableNode","kind":"Mdef","node":{".class":"FuncDef","abstract_status":0,"arg_kinds":[0],"arg_names":["self"],"dataclass_transform_spec":null,"flags":[],"fullname":"pytorch_lightning.utilities.combined_loader._Sequential.__next__","name":"__next__","type":{".class":"CallableType","arg_kinds":[0],"arg_names":["self"],"arg_types":["pytorch_lightning.utilities.combined_loader._Sequential"],"bound_args":[],"def_extras":{"first_arg":"self"},"fallback":"builtins.function","from_concatenate":false,"implicit":false,"is_ellipsis_args":false,"name":"__next__ of _Sequential","ret_type":{".class":"TupleType","implicit":false,"items":[{".class":"AnyType","missing_import_name":null,"source_any":null,"type_of_any":2},"builtins.int","builtins.int"],"partial_fallback":{".class":"Instance","args":[{".class":"AnyType","missing_import_name":null,"source_any":null,"type_of_any":6}],"type_ref":"builtins.tuple"}},"type_guard":null,"unpack_kwargs":false,"variables":[]}}},"_idx":{".class":"SymbolTableNode","implicit":true,"kind":"Mdef","node":{".class":"Var","flags":["is_inferred"],"fullname":"pytorch_lightning.utilities.combined_loader._Sequential._idx","name":"_idx","type":"builtins.int"}},"_iterator_idx":{".class":"SymbolTableNode","implicit":true,"kind":"Mdef","node":{".class":"Var","flags":["is_inferred"],"fullname":"pytorch_lightning.utilities.combined_loader._Sequential._iterator_idx","name":"_iterator_idx","type":"builtins.int"}},"_limits":{".class":"SymbolTableNode","implicit":true,"kind":"Mdef","node":{".class":"Var","flags":["is_inferred"],"fullname":"pytorch_lightning.utilities.combined_loader._Sequential._limits","name":"_limits","type":{".class":"UnionType","items":[{".class":"Instance","args":[{".class":"UnionType","items":["builtins.int","builtins.float"]}],"type_ref":"builtins.list"},{".class":"NoneType"}]}}},"_use_next_iterator":{".class":"SymbolTableNode","kind":"Mdef","node":{".class":"FuncDef","abstract_status":0,"arg_kinds":[0],"arg_names":["self"],"dataclass_transform_spec":null,"flags":[],"fullname":"pytorch_lightning.utilities.combined_loader._Sequential._use_next_iterator","name":"_use_next_iterator","type":{".class":"CallableType","arg_kinds":[0],"arg_names":["self"],"arg_types":["pytorch_lightning.utilities.combined_loader._Sequential"],"bound_args":[],"def_extras":{"first_arg":"self"},"fallback":"builtins.function","from_concatenate":false,"implicit":false,"is_ellipsis_args":false,"name":"_use_next_iterator of _Sequential","ret_type":{".class":"NoneType"},"type_guard":null,"unpack_kwargs":false,"variables":[]}}},"limits":{".class":"SymbolTableNode","kind":"Mdef","node":{".class":"OverloadedFuncDef","flags":["is_property"],"fullname":"pytorch_lightning.utilities.combined_loader._Sequential.limits","impl":null,"items":[{".class":"Decorator","func":{".class":"FuncDef","abstract_status":0,"arg_kinds":[0],"arg_names":["self"],"dataclass_transform_spec":null,"flags":["is_property","is_overload","is_decorated"],"fullname":"pytorch_lightning.utilities.combined_loader._Sequential.limits","name":"limits","type":{".class":"CallableType","arg_kinds":[0],"arg_names":["self"],"arg_types":["pytorch_lightning.utilities.combined_loader._Sequential"],"bound_args":[],"def_extras":{"first_arg":"self"},"fallback":"builtins.function","from_concatenate":false,"implicit":false,"is_ellipsis_args":false,"name":"limits of _Sequential","ret_type":{".class":"UnionType","items":[{".class":"Instance","args":[{".class":"UnionType","items":["builtins.int","builtins.float"]}],"type_ref":"builtins.list"},{".class":"NoneType"}]},"type_guard":null,"unpack_kwargs":false,"variables":[]}},"is_overload":true,"var":{".class":"Var","flags":["is_initialized_in_class","is_property","is_settable_property","is_ready","is_inferred"],"fullname":"pytorch_lightning.utilities.combined_loader._Sequential.limits","name":"limits","type":{".class":"CallableType","arg_kinds":[0],"arg_names":["self"],"arg_types":["pytorch_lightning.utilities.combined_loader._Sequential"],"bound_args":[],"def_extras":{"first_arg":"self"},"fallback":"builtins.function","from_concatenate":false,"implicit":false,"is_ellipsis_args":false,"name":"limits of _Sequential","ret_type":{".class":"UnionType","items":[{".class":"Instance","args":[{".class":"UnionType","items":["builtins.int","builtins.float"]}],"type_ref":"builtins.list"},{".class":"NoneType"}]},"type_guard":null,"unpack_kwargs":false,"variables":[]}}},{".class":"Decorator","func":{".class":"FuncDef","abstract_status":0,"arg_kinds":[0,0],"arg_names":["self","limits"],"dataclass_transform_spec":null,"flags":["is_decorated"],"fullname":"pytorch_lightning.utilities.combined_loader._Sequential.limits","name":"limits","type":{".class":"CallableType","arg_kinds":[0,0],"arg_names":["self","limits"],"arg_types":["pytorch_lightning.utilities.combined_loader._Sequential",{".class":"UnionType","items":[{".class":"Instance","args":[{".class":"UnionType","items":["builtins.int","builtins.float"]}],"type_ref":"builtins.list"},{".class":"NoneType"}]}],"bound_args":[],"def_extras":{"first_arg":"self"},"fallback":"builtins.function","from_concatenate":false,"implicit":false,"is_ellipsis_args":false,"name":"limits of _Sequential","ret_type":{".class":"NoneType"},"type_guard":null,"unpack_kwargs":false,"variables":[]}},"is_overload":false,"var":{".class":"Var","flags":["is_inferred"],"fullname":"","name":"limits","type":null}}],"type":{".class":"Overloaded","items":[{".class":"CallableType","arg_kinds":[0],"arg_names":["self"],"arg_types":["pytorch_lightning.utilities.combined_loader._Sequential"],"bound_args":[],"def_extras":{"first_arg":"self"},"fallback":"builtins.function","from_concatenate":false,"implicit":false,"is_ellipsis_args":false,"name":"limits of _Sequential","ret_type":{".class":"UnionType","items":[{".class":"Instance","args":[{".class":"UnionType","items":["builtins.int","builtins.float"]}],"type_ref":"builtins.list"},{".class":"NoneType"}]},"type_guard":null,"unpack_kwargs":false,"variables":[]}]}}},"reset":{".class":"SymbolTableNode","kind":"Mdef","node":{".class":"FuncDef","abstract_status":0,"arg_kinds":[0],"arg_names":["self"],"dataclass_transform_spec":null,"flags":[],"fullname":"pytorch_lightning.utilities.combined_loader._Sequential.reset","name":"reset","type":{".class":"CallableType","arg_kinds":[0],"arg_names":["self"],"arg_types":["pytorch_lightning.utilities.combined_loader._Sequential"],"bound_args":[],"def_extras":{"first_arg":"self"},"fallback":"builtins.function","from_concatenate":false,"implicit":false,"is_ellipsis_args":false,"name":"reset of _Sequential","ret_type":{".class":"NoneType"},"type_guard":null,"unpack_kwargs":false,"variables":[]}}}},"self_type":{".class":"TypeVarType","fullname":"pytorch_lightning.utilities.combined_loader._Sequential.Self","id":0,"name":"Self","namespace":"","upper_bound":"pytorch_lightning.utilities.combined_loader._Sequential","values":[],"variance":0},"slots":null,"tuple_type":null,"type_vars":[],"typeddict_type":null}},"_T":{".class":"SymbolTableNode","kind":"Gdef","node":{".class":"TypeVarExpr","fullname":"pytorch_lightning.utilities.combined_loader._T","name":"_T","upper_bound":"builtins.object","values":[],"variance":0}},"__annotations__":{".class":"SymbolTableNode","kind":"Gdef","node":{".class":"Var","flags":["is_ready"],"fullname":"pytorch_lightning.utilities.combined_loader.__annotations__","name":"__annotations__","type":{".class":"Instance","args":["builtins.str",{".class":"AnyType","missing_import_name":null,"source_any":null,"type_of_any":6}],"type_ref":"builtins.dict"}}},"__doc__":{".class":"SymbolTableNode","kind":"Gdef","node":{".class":"Var","flags":["is_ready"],"fullname":"pytorch_lightning.utilities.combined_loader.__doc__","name":"__doc__","type":"builtins.str"}},"__file__":{".class":"SymbolTableNode","kind":"Gdef","node":{".class":"Var","flags":["is_ready"],"fullname":"pytorch_lightning.utilities.combined_loader.__file__","name":"__file__","type":"builtins.str"}},"__name__":{".class":"SymbolTableNode","kind":"Gdef","node":{".class":"Var","flags":["is_ready"],"fullname":"pytorch_lightning.utilities.combined_loader.__name__","name":"__name__","type":"builtins.str"}},"__package__":{".class":"SymbolTableNode","kind":"Gdef","node":{".class":"Var","flags":["is_ready"],"fullname":"pytorch_lightning.utilities.combined_loader.__package__","name":"__package__","type":"builtins.str"}},"_map_and_unflatten":{".class":"SymbolTableNode","cross_ref":"pytorch_lightning.utilities._pytree._map_and_unflatten","kind":"Gdef"},"_shutdown_workers_and_reset_iterator":{".class":"SymbolTableNode","kind":"Gdef","node":{".class":"FuncDef","abstract_status":0,"arg_kinds":[0],"arg_names":["dataloader"],"dataclass_transform_spec":null,"flags":[],"fullname":"pytorch_lightning.utilities.combined_loader._shutdown_workers_and_reset_iterator","name":"_shutdown_workers_and_reset_iterator","type":{".class":"CallableType","arg_kinds":[0],"arg_names":["dataloader"],"arg_types":["builtins.object"],"bound_args":[],"def_extras":{"first_arg":null},"fallback":"builtins.function","from_concatenate":false,"implicit":false,"is_ellipsis_args":false,"name":"_shutdown_workers_and_reset_iterator","ret_type":{".class":"NoneType"},"type_guard":null,"unpack_kwargs":false,"variables":[]}}},"_tree_flatten":{".class":"SymbolTableNode","cross_ref":"pytorch_lightning.utilities._pytree._tree_flatten","kind":"Gdef"},"sized_len":{".class":"SymbolTableNode","kind":"Gdef","node":{".class":"Var","flags":["is_suppressed_import","is_ready","is_inferred"],"fullname":"pytorch_lightning.utilities.combined_loader.sized_len","name":"sized_len","type":{".class":"AnyType","missing_import_name":"pytorch_lightning.utilities.combined_loader.sized_len","source_any":null,"type_of_any":3}}},"tree_unflatten":{".class":"SymbolTableNode","cross_ref":"torch.utils._pytree.tree_unflatten","kind":"Gdef"}},"path":"/home/afe/.local/lib/python3.10/site-packages/pytorch_lightning/utilities/combined_loader.py"}